json_arrays/__init__.py
json_arrays/_types.py
json_arrays/exceptions.py
json_arrays/files.py
json_arrays/json_iter.py
json_arrays/jsonl_iter.py
json_arrays/py.typed
json_arrays/encoders/__init__.py
json_arrays/encoders/decimal_encoders.py
json_arrays/jsonlib/__init__.py
json_arrays/jsonlib/backends/__init__.py
json_arrays/jsonlib/backends/be_json.py
json_arrays/jsonlib/backends/be_orjson.py
json_arrays/shared/__init__.py
json_arrays/shared/writer.py
json_arrays/utility/__init__.py
json_arrays-0.15.0.dist-info/METADATA
json_arrays-0.15.0.dist-info/WHEEL
json_arrays-0.15.0.dist-info/RECORD
