Metadata-Version: 2.3
Name: json-arrays
Version: 0.15.0
Summary: Stream JSON and JSON-Lines lazily.
Project-URL: Homepage, https://github.com/spraakbanken/json-arrays-py
Project-URL: Repository, https://github.com/spraakbanken/json-arrays-py
Project-URL: Bug Tracker, https://github.com/spraakbanken/json-arrays-py/issues
Author-email: Språkbanken Text <sb-info@svenska.gu.se>, Kristoffer Andersson <kristoffer.andersson@gu.se>
License: MIT
Classifier: Development Status :: 4 - Beta
Classifier: Intended Audience :: Developers
Classifier: License :: OSI Approved :: MIT License
Classifier: Operating System :: POSIX
Classifier: Operating System :: Unix
Classifier: Programming Language :: Python :: 3.9
Classifier: Programming Language :: Python :: 3.10
Classifier: Programming Language :: Python :: 3.11
Classifier: Programming Language :: Python :: 3.12
Classifier: Programming Language :: Python :: Implementation :: CPython
Classifier: Topic :: Utilities
Requires-Python: >=3.9
Requires-Dist: ijson>=3.2.3
Provides-Extra: orjson
Requires-Dist: orjson>=3.9.13; extra == 'orjson'
